flask_grpc/__init__.py
flask_grpc-0.1.1.dist-info/LICENSE
flask_grpc-0.1.1.dist-info/WHEEL
flask_grpc-0.1.1.dist-info/METADATA
flask_grpc-0.1.1.dist-info/RECORD
