Metadata-Version: 2.1
Name: flask-grpc
Version: 0.1.1
Summary: A grpc client for Flask.
License: BSD-3-Clause
Author: codeif
Author-email: me@codeif.com
Requires-Python: >=3.8,<4.0
Classifier: License :: OSI Approved :: BSD License
Classifier: Programming Language :: Python :: 3
Classifier: Programming Language :: Python :: 3.10
Classifier: Programming Language :: Python :: 3.8
Classifier: Programming Language :: Python :: 3.9
Requires-Dist: Flask (>=1.0.0)
Requires-Dist: grpcio (>=1.0.0)
Requires-Dist: protobuf (>3.0.0)
